setup.py
./pyquicksetup/__init__.py
./pyquicksetup/helper.py
./pyquicksetup/pyquick.py
./pyquicksetup/simple.py
pyquicksetup.egg-info/PKG-INFO
pyquicksetup.egg-info/SOURCES.txt
pyquicksetup.egg-info/dependency_links.txt
pyquicksetup.egg-info/requires.txt
pyquicksetup.egg-info/top_level.txt